attrdict/__init__.py
attrdict/default.py
attrdict/dictionary.py
attrdict/mapping.py
attrdict/merge.py
attrdict/mixins.py
pytive/__init__.py
pytive-0.0.1.dist-info/LICENSE.txt
pytive-0.0.1.dist-info/METADATA
pytive-0.0.1.dist-info/WHEEL
pytive-0.0.1.dist-info/top_level.txt
pytive-0.0.1.dist-info/RECORD
