Metadata-Version: 2.1
Name: pytive
Version: 0.0.1
Summary: Mirrativ PythonApi
Home-page: https://github.com/koaf/pytive
Author: koaf
Author-email: koafff@aol.com
Classifier: Programming Language :: Python :: 3.7
Classifier: License :: OSI Approved :: MIT License
Classifier: Operating System :: OS Independent
License-File: LICENSE.txt
